neurips_downloader/__init_.py
neurips_downloader/core.py
neurips_downloader/commands/download_proceeding_by_year.py
neurips_downloader-0.1.2.dist-info/METADATA
neurips_downloader-0.1.2.dist-info/WHEEL
neurips_downloader-0.1.2.dist-info/top_level.txt
neurips_downloader-0.1.2.dist-info/RECORD
