Metadata-Version: 2.4
Name: neurips-downloader
Version: 0.1.2
Summary: Add your description here
Requires-Python: >=3.11.5
Requires-Dist: beautifulsoup4>=4.13.3
Requires-Dist: requests>=2.32.3
Requires-Dist: rich>=13.9.4
Requires-Dist: sienna>=0.2.6
